{
  "name": "default",
  "storeId": "alkhbaz",
  "channelId": null,
  "isAnonymous": false,
  "customerId": "af860464-435e-4558-b87a-21f7bd4c1cb7",
  "customerName": "yyy yyyy",
  "organizationId": null,
  "currency": "EGP",
  "languageCode": "ar-EG",
  "taxIncluded": null,
  "isRecuring": false,
  "comment": null,
  "status": null,
  "purchaseOrderNumber": null,
  "weightUnit": null,
  "weight": null,
  "validationType": null,
  "type": null,
  "volumetricWeight": null,
  "total": 370.75,
  "subTotal": 290.44,
  "subTotalWithTax": 320.75,
  "subTotalDiscount": 0,
  "subTotalDiscountWithTax": 0,
  "shippingTotal": 50,
  "shippingTotalWithTax": 50,
  "shippingSubTotal": 50,
  "shippingSubTotalWithTax": 50,
  "shippingDiscountTotal": 0,
  "shippingDiscountTotalWithTax": 0,
  "paymentTotal": 0,
  "paymentTotalWithTax": 0,
  "paymentSubTotal": 0,
  "paymentSubTotalWithTax": 0,
  "paymentDiscountTotal": 0,
  "paymentDiscountTotalWithTax": 0,
  "handlingTotal": 0,
  "handlingTotalWithTax": 0,
  "discountAmount": 0,
  "discountAmountWithTax": 0,
  "discountTotal": 0,
  "discountTotalWithTax": 0,
  "fee": 0,
  "feeWithTax": 0,
  "feeTotal": 0,
  "feeTotalWithTax": 0,
  "addresses": [
    {
      "addressType": "BillingAndShipping",
      "key": "51174963-16df-4247-8587-aa08564c3d36",
      "name": "المنزل",
      "organization": null,
      "countryCode": "EGY",
      "countryName": "Egypt",
      "city": "حدايق أكتوبر / مونت فيو",
      "postalCode": "7015",
      "zip": null,
      "line1": "رقم المبني: y/ رقم الدور:7/ رقم الشقة :y",
      "line2": " ghghg",
      "regionId": null,
      "regionName": null,
      "firstName": "yyy",
      "middleName": null,
      "lastName": "yyyy",
      "phone": "01111122548",
      "email": "ghgh@dff.vvv",
      "outerId": null,
      "isDefault": false,
      "description": null
    }
  ],
  "items": [
    {
      "productId": "8016-2",
      "catalogId": "0a841b7e-c732-4738-913d-9e43c054170e",
      "categoryId": "111015000000",
      "sku": "8016-2",
      "productType": "Physical",
      "name": "جلاش صوابع كريمة 1/2 كيلو",
      "quantity": 1,
      "fulfillmentCenterId": "140101000000",
      "fulfillmentCenterName": "المعادي",
      "fulfillmentLocationCode": null,
      "shipmentMethodCode": null,
      "requiredShipping": true,
      "thumbnailImageUrl": null,
      "imageUrl": "http://20.163.148.155:9070/assets/catalog/0a841/8016/8016.jpg",
      "isGift": false,
      "isRejected": false,
      "currency": "EGP",
      "languageCode": null,
      "note": null,
      "isReccuring": false,
      "taxIncluded": false,
      "volumetricWeight": null,
      "weightUnit": null,
      "weight": null,
      "measureUnit": null,
      "height": null,
      "length": null,
      "width": null,
      "validationType": null,
      "isReadOnly": false,
      "priceId": "83f0eea5-fccb-4420-a88d-19eb7aab8096",
      "listPrice": 115,
      "listPriceWithTax": 120.75,
      "salePrice": 115,
      "salePriceWithTax": 120.75,
      "placedPrice": 115,
      "placedPriceWithTax": 120.75,
      "extendedPrice": 115,
      "extendedPriceWithTax": 120.75,
      "discountAmount": 0,
      "discountAmountWithTax": 0,
      "discountTotal": 0,
      "discountTotalWithTax": 0,
      "fee": 0,
      "feeWithTax": 0,
      "vendorId": null,
      "discounts": null,
      "taxType": "5",
      "taxTotal": 5.75,
      "taxPercentRate": 0.05,
      "taxDetails": null,
      "objectType": "TotPlatform.CartModule.Core.Model.LineItem",
      "dynamicProperties": [],
      "createdDate": "2023-10-17T12:02:52.020963Z",
      "modifiedDate": "2023-10-17T12:02:52.020963Z",
      "createdBy": "33bf4db2-ab9c-4757-8efe-0935b231edc8",
      "modifiedBy": "33bf4db2-ab9c-4757-8efe-0935b231edc8",
      "id": "99e605fb-629f-4225-85f6-fde50c81a43e"
    },
    {
      "productId": "8003",
      "catalogId": "0a841b7e-c732-4738-913d-9e43c054170e",
      "categoryId": "111015000000",
      "sku": "8003",
      "productType": "Physical",
      "name": "بسبوسة بندق",
      "quantity": 1,
      "fulfillmentCenterId": "140101000000",
      "fulfillmentCenterName": "المعادي",
      "fulfillmentLocationCode": null,
      "shipmentMethodCode": null,
      "requiredShipping": true,
      "thumbnailImageUrl": null,
      "imageUrl": "http://20.163.148.155:9070/assets/catalog/0a841/8003/8003.jpg",
      "isGift": false,
      "isRejected": false,
      "currency": "EGP",
      "languageCode": null,
      "note": null,
      "isReccuring": false,
      "taxIncluded": false,
      "volumetricWeight": null,
      "weightUnit": null,
      "weight": null,
      "measureUnit": null,
      "height": null,
      "length": null,
      "width": null,
      "validationType": null,
      "isReadOnly": false,
      "priceId": "83f0eea5-fccb-4420-a88d-19eb7aab8096",
      "listPrice": 175.44,
      "listPriceWithTax": 200.0016,
      "salePrice": 175.44,
      "salePriceWithTax": 200.0016,
      "placedPrice": 175.44,
      "placedPriceWithTax": 200.0016,
      "extendedPrice": 175.44,
      "extendedPriceWithTax": 200.0016,
      "discountAmount": 0,
      "discountAmountWithTax": 0,
      "discountTotal": 0,
      "discountTotalWithTax": 0,
      "fee": 0,
      "feeWithTax": 0,
      "vendorId": null,
      "discounts": null,
      "taxType": "14",
      "taxTotal": 24.5616,
      "taxPercentRate": 0.14,
      "taxDetails": null,
      "objectType": "TotPlatform.CartModule.Core.Model.LineItem",
      "dynamicProperties": [],
      "createdDate": "2023-10-17T12:02:44.3676866Z",
      "modifiedDate": "2023-10-17T12:02:52.0210737Z",
      "createdBy": "33bf4db2-ab9c-4757-8efe-0935b231edc8",
      "modifiedBy": "33bf4db2-ab9c-4757-8efe-0935b231edc8",
      "id": "c6cad9ac-fada-4b1c-a724-dece13f469fb"
    }
  ],
  "payments": [],
  "shipments": [
    {
      "shipmentMethodCode": "ZoneRate",
      "shipmentMethodOption": null,
      "fulfillmentCenterId": "140301000000",
      "fulfillmentCenterName": "اكتوبر",
      "warehouseLocation": null,
      "currency": "EGP",
      "volumetricWeight": null,
      "weightUnit": null,
      "weight": null,
      "measureUnit": null,
      "height": null,
      "length": null,
      "width": null,
      "price": 50,
      "priceWithTax": 50,
      "total": 50,
      "totalWithTax": 50,
      "discountAmount": 0,
      "discountAmountWithTax": 0,
      "fee": 0,
      "feeWithTax": 0,
      "vendorId": null,
      "comment": null,
      "taxType": null,
      "taxTotal": 0,
      "taxPercentRate": 0,
      "deliveryAddress": {
        "addressType": "BillingAndShipping",
        "key": "b2e984ea-1728-4488-81a9-f6c142f872ef",
        "name": "المنزل",
        "organization": null,
        "countryCode": "EGY",
        "countryName": "Egypt",
        "city": "حدايق أكتوبر / مونت فيو",
        "postalCode": "7015",
        "zip": null,
        "line1": "رقم المبني: y/ رقم الدور:7/ رقم الشقة :y",
        "line2": " ghghg",
        "regionId": null,
        "regionName": null,
        "firstName": "yyy",
        "middleName": null,
        "lastName": "yyyy",
        "phone": "01111122548",
        "email": "ghgh@dff.vvv",
        "outerId": null,
        "isDefault": false,
        "description": null
      },
      "items": null,
      "discounts": null,
      "taxDetails": null,
      "objectType": "TotPlatform.CartModule.Core.Model.Shipment",
      "dynamicProperties": [],
      "createdDate": "2023-10-17T19:30:12.5488596Z",
      "modifiedDate": "2023-10-17T19:30:12.5488596Z",
      "createdBy": "33bf4db2-ab9c-4757-8efe-0935b231edc8",
      "modifiedBy": "33bf4db2-ab9c-4757-8efe-0935b231edc8",
      "id": "8108717c-23b0-489f-ac60-558628319075"
    }
  ],
  "coupons": [],
  "coupon": null,
  "discounts": [],
  "taxType": null,
  "taxTotal": 30.31,
  "taxPercentRate": 0,
  "taxDetails": [],
  "objectType": "TotPlatform.CartModule.Core.Model.ShoppingCart",
  "dynamicProperties": [],
  "createdDate": "2023-10-17T11:59:20.1467537Z",
  "modifiedDate": "2023-10-17T19:30:12.5489498Z",
  "createdBy": "33bf4db2-ab9c-4757-8efe-0935b231edc8",
  "modifiedBy": "33bf4db2-ab9c-4757-8efe-0935b231edc8",
  "id": "e078e59e-08d1-4e05-9648-29ec2c44ae8b"
}
